disuniter.py
dis_uniter-1.4.0.dist-info/WHEEL
dis_uniter-1.4.0.dist-info/METADATA
dis_uniter-1.4.0.dist-info/RECORD
