Metadata-Version: 2.1
Name: dis-uniter
Version: 1.4.0
Summary: Keep your discord bot alive on replit
Author: Umar Sharief
Author-email: umar.sharief04@gmail.com
Requires-Python: >=3.8,<4.0
Classifier: Programming Language :: Python :: 3
Classifier: Programming Language :: Python :: 3.8
Classifier: Programming Language :: Python :: 3.9
Classifier: Programming Language :: Python :: 3.10
